Metadata-Version: 2.4
Name: abx-spec-extractor
Version: 0.1.0
Summary: Add your description here
Requires-Python: >=3.10
Requires-Dist: abx>=0.1.0
Requires-Dist: pydantic>=2.5.0
Requires-Dist: python-benedict>=0.26.0
